zangy-0.1.2.dist-info/METADATA
zangy-0.1.2.dist-info/WHEEL
zangy.cp39-win_amd64.pyd
zangy-0.1.2.dist-info/RECORD
