Metadata-Version: 2.1
Name: zangy
Version: 0.1.2
Summary: A fast redis library written in Rust
Keywords: fast redis
Home-Page: https://github.com/Gelbpunkt/zangy
Author: Jens Reidel <adrian@travitia.xyz>
Author-Email: Jens Reidel <adrian@travitia.xyz>
License: MIT
Requires-Python: >=3.8
